{
  "name": "TAS — Stale Workflow Detection & Deactivation",
  "nodes": [
    {
      "parameters": {
        "rule": {
          "interval": [
            {
              "field": "cronExpression",
              "expression": "0 6 * * *"
            }
          ]
        }
      },
      "id": "trigger-daily-6am",
      "name": "Daily 6AM",
      "type": "n8n-nodes-base.scheduleTrigger",
      "typeVersion": 1.2,
      "position": [0, 0]
    },
    {
      "parameters": {
        "jsCode": "// ╔══════════════════════════════════════════════════════╗\n// ║  CONFIGURATION — Edit these values to customise     ║\n// ╚══════════════════════════════════════════════════════╝\nconst CONFIG = {\n  // Workflows not updated in this many days are considered stale\n  STALE_DAYS: 90,\n\n  // Email recipient for the summary report\n  EMAIL_RECIPIENT: 'fabian@fdnxt.com',\n\n  // Google Sheet ID for the central TAS_N8N_Audit sheet\n  // Create one sheet, share with your n8n service account, paste ID here\n  SHEET_ID: $env.TAS_AUDIT_SHEET_ID || 'YOUR_GOOGLE_SHEET_ID_HERE',\n\n  // Tab name within the audit sheet\n  SHEET_TAB: 'Stale_Workflows',\n\n  // Set to true to actually deactivate stale workflows\n  // Set to false for dry-run / report-only mode\n  AUTO_DEACTIVATE: true,\n\n  // Workflow name patterns to NEVER deactivate (regex strings)\n  PROTECTED_PATTERNS: [\n    'TAS.*Audit',\n    'TAS.*Stale',\n    'TAS.*Cleanup',\n    'TAS.*Organiser',\n    'Critical',\n    'Production'\n  ]\n};\n\nreturn [{ json: CONFIG }];"
      },
      "id": "config",
      "name": "⚙️ Configuration",
      "type": "n8n-nodes-base.code",
      "typeVersion": 2,
      "position": [220, 0]
    },
    {
      "parameters": {
        "method": "GET",
        "url": "={{ $env.N8N_BASE_URL }}/api/v1/workflows",
        "authentication": "genericCredentialType",
        "genericAuthType": "httpHeaderAuth",
        "options": {}
      },
      "id": "fetch-workflows",
      "name": "Fetch All Workflows",
      "type": "n8n-nodes-base.httpRequest",
      "typeVersion": 4.2,
      "position": [440, 0],
      "credentials": {
        "httpHeaderAuth": {
          "id": "n8n-api-key",
          "name": "n8n API Key"
        }
      }
    },
    {
      "parameters": {
        "jsCode": "const config = $('⚙️ Configuration').first().json;\nconst workflows = $input.first().json.data || [];\nconst now = new Date();\nconst protectedPatterns = config.PROTECTED_PATTERNS.map(p => new RegExp(p, 'i'));\n\nconst results = [];\n\nfor (const wf of workflows) {\n  const updatedAt = new Date(wf.updatedAt);\n  const createdAt = new Date(wf.createdAt);\n  const daysSinceUpdate = Math.floor((now - updatedAt) / (1000 * 60 * 60 * 24));\n  const daysSinceCreated = Math.floor((now - createdAt) / (1000 * 60 * 60 * 24));\n  const isStale = daysSinceUpdate > config.STALE_DAYS;\n  const isProtected = protectedPatterns.some(p => p.test(wf.name));\n  const tagNames = (wf.tags || []).map(t => t.name).join(', ');\n\n  let action = 'NONE';\n  let reason = '';\n\n  if (isStale && wf.active && !isProtected && config.AUTO_DEACTIVATE) {\n    action = 'DEACTIVATE';\n    reason = `Active but untouched for ${daysSinceUpdate} days`;\n  } else if (isStale && wf.active && isProtected) {\n    action = 'PROTECTED_SKIP';\n    reason = `Stale but matches protected pattern — skipped`;\n  } else if (isStale && !wf.active) {\n    action = 'FLAG_INACTIVE';\n    reason = `Already inactive, untouched ${daysSinceUpdate} days — candidate for deletion`;\n  } else {\n    action = 'OK';\n    reason = 'Within retention window';\n  }\n\n  results.push({\n    workflowId: wf.id,\n    workflowName: wf.name,\n    active: wf.active,\n    tags: tagNames,\n    createdAt: wf.createdAt,\n    updatedAt: wf.updatedAt,\n    daysSinceUpdate,\n    daysSinceCreated,\n    isStale,\n    isProtected,\n    action,\n    reason,\n    timestamp: now.toISOString()\n  });\n}\n\n// Sort: actionable items first\nresults.sort((a, b) => {\n  const order = { DEACTIVATE: 0, PROTECTED_SKIP: 1, FLAG_INACTIVE: 2, OK: 3 };\n  return (order[a.action] || 99) - (order[b.action] || 99);\n});\n\nreturn results.map(r => ({ json: r }));"
      },
      "id": "analyse-staleness",
      "name": "Analyse Staleness",
      "type": "n8n-nodes-base.code",
      "typeVersion": 2,
      "position": [660, 0]
    },
    {
      "parameters": {
        "conditions": {
          "options": { "caseSensitive": true, "leftValue": "", "typeValidation": "strict" },
          "conditions": [
            {
              "id": "deactivate-check",
              "leftValue": "={{ $json.action }}",
              "rightValue": "DEACTIVATE",
              "operator": { "type": "string", "operation": "equals" }
            }
          ],
          "combinator": "and"
        },
        "options": {}
      },
      "id": "filter-deactivate",
      "name": "Needs Deactivation?",
      "type": "n8n-nodes-base.filter",
      "typeVersion": 2,
      "position": [880, -140]
    },
    {
      "parameters": {
        "method": "POST",
        "url": "={{ $env.N8N_BASE_URL }}/api/v1/workflows/{{ $json.workflowId }}/deactivate",
        "authentication": "genericCredentialType",
        "genericAuthType": "httpHeaderAuth",
        "options": {}
      },
      "id": "deactivate-workflow",
      "name": "Deactivate Workflow",
      "type": "n8n-nodes-base.httpRequest",
      "typeVersion": 4.2,
      "position": [1100, -140],
      "credentials": {
        "httpHeaderAuth": {
          "id": "n8n-api-key",
          "name": "n8n API Key"
        }
      }
    },
    {
      "parameters": {
        "conditions": {
          "options": { "caseSensitive": true, "leftValue": "", "typeValidation": "strict" },
          "conditions": [
            {
              "id": "stale-check",
              "leftValue": "={{ $json.isStale }}",
              "rightValue": true,
              "operator": { "type": "boolean", "operation": "equals", "singleValue": true }
            }
          ],
          "combinator": "and"
        },
        "options": {}
      },
      "id": "filter-stale-for-sheet",
      "name": "Filter Stale for Audit",
      "type": "n8n-nodes-base.filter",
      "typeVersion": 2,
      "position": [880, 0]
    },
    {
      "parameters": {
        "operation": "appendOrUpdate",
        "documentId": { "__rl": true, "mode": "id", "value": "={{ $('⚙️ Configuration').first().json.SHEET_ID }}" },
        "sheetName": { "__rl": true, "mode": "name", "value": "Stale_Workflows" },
        "columns": {
          "mappingMode": "defineBelow",
          "value": {
            "Timestamp": "={{ $json.timestamp }}",
            "Workflow ID": "={{ $json.workflowId }}",
            "Workflow Name": "={{ $json.workflowName }}",
            "Active": "={{ $json.active }}",
            "Tags": "={{ $json.tags }}",
            "Days Since Update": "={{ $json.daysSinceUpdate }}",
            "Days Since Created": "={{ $json.daysSinceCreated }}",
            "Action": "={{ $json.action }}",
            "Reason": "={{ $json.reason }}",
            "Protected": "={{ $json.isProtected }}"
          }
        },
        "options": {}
      },
      "id": "log-to-sheet",
      "name": "Log to Audit Sheet",
      "type": "n8n-nodes-base.googleSheets",
      "typeVersion": 4.5,
      "position": [1100, 0],
      "credentials": {
        "googleSheetsOAuth2Api": {
          "id": "google-sheets-cred",
          "name": "Google Sheets OAuth2"
        }
      }
    },
    {
      "parameters": {
        "jsCode": "const allItems = $('Analyse Staleness').all();\nconst config = $('⚙️ Configuration').first().json;\n\nconst deactivated = allItems.filter(i => i.json.action === 'DEACTIVATE');\nconst protectedSkipped = allItems.filter(i => i.json.action === 'PROTECTED_SKIP');\nconst flaggedInactive = allItems.filter(i => i.json.action === 'FLAG_INACTIVE');\nconst ok = allItems.filter(i => i.json.action === 'OK');\n\nconst tableRows = allItems\n  .filter(i => i.json.isStale)\n  .map(i => {\n    const w = i.json;\n    const badge = w.action === 'DEACTIVATE' ? '🔴 DEACTIVATED'\n      : w.action === 'PROTECTED_SKIP' ? '🛡️ PROTECTED'\n      : w.action === 'FLAG_INACTIVE' ? '⚠️ INACTIVE/STALE'\n      : '✅ OK';\n    return `<tr><td>${w.workflowName}</td><td>${w.workflowId}</td><td>${w.daysSinceUpdate}d</td><td>${w.tags || 'none'}</td><td>${badge}</td><td>${w.reason}</td></tr>`;\n  }).join('');\n\nconst html = `\n<h2>🔍 TAS Stale Workflow Report</h2>\n<p><strong>Run:</strong> ${new Date().toISOString()}</p>\n<p><strong>Threshold:</strong> ${config.STALE_DAYS} days</p>\n<hr>\n<table style=\"border-collapse:collapse;width:100%\">\n<tr><th>Metric</th><th>Count</th></tr>\n<tr><td>Total workflows scanned</td><td><strong>${allItems.length}</strong></td></tr>\n<tr><td>🔴 Deactivated this run</td><td><strong>${deactivated.length}</strong></td></tr>\n<tr><td>🛡️ Protected (skipped)</td><td><strong>${protectedSkipped.length}</strong></td></tr>\n<tr><td>⚠️ Flagged inactive/stale</td><td><strong>${flaggedInactive.length}</strong></td></tr>\n<tr><td>✅ Healthy</td><td><strong>${ok.length}</strong></td></tr>\n</table>\n<hr>\n<h3>Stale Workflow Details</h3>\n<table style=\"border-collapse:collapse;width:100%\" border=\"1\" cellpadding=\"6\">\n<tr><th>Name</th><th>ID</th><th>Age</th><th>Tags</th><th>Action</th><th>Reason</th></tr>\n${tableRows || '<tr><td colspan=\"6\">No stale workflows found 🎉</td></tr>'}\n</table>\n<hr>\n<p><em>Full audit trail logged to Google Sheet: TAS_N8N_Audit → Stale_Workflows</em></p>\n`;\n\nreturn [{ json: { html, recipient: config.EMAIL_RECIPIENT, subject: `TAS N8N Audit: ${deactivated.length} deactivated, ${flaggedInactive.length} flagged — ${allItems.length} scanned` } }];"
      },
      "id": "build-email",
      "name": "Build Email Report",
      "type": "n8n-nodes-base.code",
      "typeVersion": 2,
      "position": [880, 160]
    },
    {
      "parameters": {
        "sendTo": "={{ $json.recipient }}",
        "subject": "={{ $json.subject }}",
        "message": "={{ $json.html }}",
        "options": {}
      },
      "id": "send-email",
      "name": "Send Email Report",
      "type": "n8n-nodes-base.emailSend",
      "typeVersion": 2.1,
      "position": [1100, 160]
    }
  ],
  "connections": {
    "Daily 6AM": {
      "main": [
        [{ "node": "⚙️ Configuration", "type": "main", "index": 0 }]
      ]
    },
    "⚙️ Configuration": {
      "main": [
        [{ "node": "Fetch All Workflows", "type": "main", "index": 0 }]
      ]
    },
    "Fetch All Workflows": {
      "main": [
        [{ "node": "Analyse Staleness", "type": "main", "index": 0 }]
      ]
    },
    "Analyse Staleness": {
      "main": [
        [
          { "node": "Needs Deactivation?", "type": "main", "index": 0 },
          { "node": "Filter Stale for Audit", "type": "main", "index": 0 },
          { "node": "Build Email Report", "type": "main", "index": 0 }
        ]
      ]
    },
    "Needs Deactivation?": {
      "main": [
        [{ "node": "Deactivate Workflow", "type": "main", "index": 0 }]
      ]
    },
    "Filter Stale for Audit": {
      "main": [
        [{ "node": "Log to Audit Sheet", "type": "main", "index": 0 }]
      ]
    },
    "Build Email Report": {
      "main": [
        [{ "node": "Send Email Report", "type": "main", "index": 0 }]
      ]
    }
  },
  "settings": {
    "executionOrder": "v1"
  },
  "tags": [
    { "name": "TAS" },
    { "name": "maintenance" },
    { "name": "audit" }
  ]
}
